LICENSE
README.md
setup.cfg
setup.py
blns_recovery/__init__.py
blns_recovery/main.py
blns_recovery/mnemo.py
blns_recovery/recovery.py
blns_recovery.egg-info/PKG-INFO
blns_recovery.egg-info/SOURCES.txt
blns_recovery.egg-info/dependency_links.txt
blns_recovery.egg-info/entry_points.txt
blns_recovery.egg-info/requires.txt
blns_recovery.egg-info/top_level.txt
blns_recovery/tests/__init__.py
blns_recovery/tests/main.py
blns_recovery/tests/mnemo.py