Metadata-Version: 2.1
Name: blns-recovery
Version: 0.1.2
Summary: BLNS paper backup recovery tool
Home-page: https://github.com/blns-ltd/blns-recovery-python
Author: Dusan Klinec
Author-email: dusan.klinec@gmail.com
License: MIT
Classifier: Development Status :: 3 - Alpha
Classifier: Intended Audience :: Developers
Classifier: Programming Language :: Python
Classifier: Programming Language :: Python :: 2
Classifier: Programming Language :: Python :: 2.6
Classifier: Programming Language :: Python :: 2.7
Classifier: Programming Language :: Python :: 3
Classifier: Programming Language :: Python :: 3.3
Classifier: Programming Language :: Python :: 3.4
Classifier: Programming Language :: Python :: 3.5
Classifier: Topic :: Security
Provides-Extra: dev
Provides-Extra: docs
License-File: LICENSE
